rst2code
version
