Metadata-Version: 1.1
Name: rst2code
Version: 0.0.2
Summary: reStructuredText literate programming tool
Home-page: https://github.com/jmbarbier/rst2code
Author: Jean-Matthieu BARBIER
Author-email: jm.barbier@solidev.net
License: UNKNOWN
Download-URL: https://github.com/jmbarbier/rst2code/archive/v0.0.2.tar.gz
Platform: UNKNOWN
Classifier: Development Status :: 5 - Production/Stable
Classifier: Environment :: Console
Classifier: Intended Audience :: Developers
Classifier: License :: OSI Approved :: GNU General Public License v3 or later (GPLv3+)
Classifier: Operating System :: OS Independent
Classifier: Programming Language :: Python
Classifier: Topic :: Documentation
Classifier: Topic :: Software Development
Classifier: Topic :: Text Processing :: Markup
